virtual_glob/__init__.py
virtual_glob/py.typed
virtual_glob-0.2.0.dist-info/LICENSE
virtual_glob-0.2.0.dist-info/WHEEL
virtual_glob-0.2.0.dist-info/METADATA
virtual_glob-0.2.0.dist-info/RECORD
