Metadata-Version: 2.1
Name: virtual_glob
Version: 0.2.0
Summary: Globbing of virtual file systems.
Author-email: Chris Sewell <chrisj_sewell@hotmail.com>
Requires-Python: >=3.8
Classifier: License :: OSI Approved :: MIT License
Requires-Dist: pytest ; extra == "testing"
Project-URL: Home, https://github.com/chrisjsewell/virtual_glob
Provides-Extra: testing
